pandas_custom_mask
