Metadata-Version: 1.0
Name: pandas-custom-mask
Version: 0.2.0
Summary: Provides an easy way to use boolean masks for Pandas dataframes.
Home-page: https://github.com/TiesdeKok/
Author: TiesdeKok
Author-email: t.c.j.dekok@tilburguniversity.edu
License: MIT
Platform: UNKNOWN
